odoo8_addon_sale_order_import_csv-8.0.1.0.0.99.dev7-nspkg.pth
odoo_addons/sale_order_import_csv/README.rst
odoo_addons/sale_order_import_csv/__init__.py
odoo_addons/sale_order_import_csv/__openerp__.py
odoo_addons/sale_order_import_csv/i18n/sale_order_import_csv.pot
odoo_addons/sale_order_import_csv/static/description/icon.png
odoo_addons/sale_order_import_csv/tests/__init__.py
odoo_addons/sale_order_import_csv/tests/test_csv_order_import.py
odoo_addons/sale_order_import_csv/tests/files/order_file_test1.csv
odoo_addons/sale_order_import_csv/tests/files/order_file_test1_update.csv
odoo_addons/sale_order_import_csv/wizard/__init__.py
odoo_addons/sale_order_import_csv/wizard/sale_order_import.py
odoo8_addon_sale_order_import_csv-8.0.1.0.0.99.dev7.dist-info/METADATA
odoo8_addon_sale_order_import_csv-8.0.1.0.0.99.dev7.dist-info/WHEEL
odoo8_addon_sale_order_import_csv-8.0.1.0.0.99.dev7.dist-info/namespace_packages.txt
odoo8_addon_sale_order_import_csv-8.0.1.0.0.99.dev7.dist-info/top_level.txt
odoo8_addon_sale_order_import_csv-8.0.1.0.0.99.dev7.dist-info/RECORD
